Pandas_Market_Predictor/__init__.py
Pandas_Market_Predictor/pmp.py
Pandas_Market_Predictor-1.0.6.dist-info/LICENSE
Pandas_Market_Predictor-1.0.6.dist-info/METADATA
Pandas_Market_Predictor-1.0.6.dist-info/WHEEL
Pandas_Market_Predictor-1.0.6.dist-info/top_level.txt
Pandas_Market_Predictor-1.0.6.dist-info/RECORD
