Metadata-Version: 2.1
Name: Pandas-Market-Predictor
Version: 1.0.6
Summary: Pandas Market Predictor, is a deep learning API written in Python on top of Panda that helping you predict future price (low and high), trend of Financial market assets.
Author-email: Ouedraogo Somkieta Rahim Alex <s.r.a.ouedraogo@gmail.com>
Project-URL: Homepage, https://github.com/somkietacode/Pandas_Market_Predictor
Project-URL: Bug Tracker, https://github.com/somkietacode/Pandas_Market_Predictor/issues
Classifier: Programming Language :: Python :: 3
Classifier: License :: OSI Approved :: MIT License
Classifier: Operating System :: OS Independent
Requires-Python: >=3.7
License-File: LICENSE
Requires-Dist: numpy
Requires-Dist: pandas
Requires-Dist: Artificial-Neural-Network-Classifier
Requires-Dist: Awesome-Linear-Regression
Requires-Dist: Auto-Gradient-Boosting
Requires-Dist: importlib-metadata ; python_version < "3.7"
